Metadata-Version: 2.1
Name: cac
Version: 1.0.0
Summary: Content-Aware Computing library
Home-page: https://github.com/FujitsuLaboratories/CAC
Author: Yasufumi Sakai
Author-email: sakaiyasufumi@fujitsu.com
Maintainer: Akihiko Kasagi
Maintainer-email: kasagi.akihiko@fujitsu.com
License: See https://github.com/FujitsuLaboratories/CAC/LICENSE
Platform: UNKNOWN
Classifier: Development Status :: 1 - Planning
Classifier: Environment :: Console
Classifier: Intended Audience :: Developers
Classifier: Intended Audience :: Information Technology
Classifier: Intended Audience :: Science/Research
Classifier: Natural Language :: English
Classifier: Operating System :: OS Independent
Classifier: Programming Language :: Python :: 3.7
Classifier: Topic :: Scientific/Engineering :: Artificial Intelligence
Classifier: Topic :: Software Development :: Libraries :: Python Modules
Requires-Python: >=3.7.0
